bug_be_gone.py
bug_be_gone-1.0.1.dist-info/licenses/LICENSE
bug_be_gone-1.0.1.dist-info/METADATA
bug_be_gone-1.0.1.dist-info/WHEEL
bug_be_gone-1.0.1.dist-info/entry_points.txt
bug_be_gone-1.0.1.dist-info/top_level.txt
bug_be_gone-1.0.1.dist-info/RECORD
