Metadata-Version: 2.4
Name: bug-be-gone
Version: 1.0.1
Summary: Automatically detect and fix Python errors - never debug again
Home-page: https://github.com/yourusername/bug-be-gone
Author: Keeg
Author-email: Keeghan@dishesandmore.com
License: Proprietary - Trial License
Project-URL: Bug Reports, https://github.com/yourusername/bug-be-gone/issues
Project-URL: Source, https://github.com/yourusername/bug-be-gone
Project-URL: Documentation, https://github.com/yourusername/bug-be-gone#readme
Keywords: debugger,error-fixing,automatic-debugging,python-errors,development-tools
Classifier: Development Status :: 4 - Beta
Classifier: Intended Audience :: Developers
Classifier: Topic :: Software Development :: Debuggers
Classifier: Topic :: Software Development :: Quality Assurance
Classifier: License :: Other/Proprietary License
Classifier: Programming Language :: Python :: 3
Classifier: Programming Language :: Python :: 3.6
Classifier: Programming Language :: Python :: 3.7
Classifier: Programming Language :: Python :: 3.8
Classifier: Programming Language :: Python :: 3.9
Classifier: Programming Language :: Python :: 3.10
Classifier: Programming Language :: Python :: 3.11
Classifier: Programming Language :: Python :: 3.12
Classifier: Operating System :: OS Independent
Requires-Python: >=3.6
License-File: LICENSE
Dynamic: author
Dynamic: author-email
Dynamic: classifier
Dynamic: description
Dynamic: description-content-type
Dynamic: home-page
Dynamic: keywords
Dynamic: license
Dynamic: license-file
Dynamic: project-url
Dynamic: requires-python
Dynamic: summary
